[
{		"Index": "110010001",
		"Grade": "13",
		"DescendType": "12",
		"DescendParam1": "108010001",
		"DescendIconIndex": "2",
		"DescendPhaseIndex1": "101010012",
		"DescendPhaseIndex2": "-1",
		"DescendPhaseIndex3": "-1",
		"DescendPhaseIndex4": "-1",
		"DescendPhaseIndex5": "-1"
	},
{
		"Index": "110010002",
		"Grade": "13",
		"DescendType": "12",
		"DescendParam1": "108010002",
		"DescendIconIndex": "3",
		"DescendPhaseIndex1": "-1",
		"DescendPhaseIndex2": "-1",
		"DescendPhaseIndex3": "-1",
		"DescendPhaseIndex4": "-1",
		"DescendPhaseIndex5": "-1"
	},
{
		"Index": "110010003",
		"Grade": "13",
		"DescendType": "12",
		"DescendParam1": "108010003",
		"DescendIconIndex": "1",
		"DescendPhaseIndex1": "101010010",
		"DescendPhaseIndex2": "-1",
		"DescendPhaseIndex3": "-1",
		"DescendPhaseIndex4": "-1",
		"DescendPhaseIndex5": "-1"
	},
{
		"Index": "110010004",
		"Grade": "14",
		"DescendType": "11",
		"DescendParam1": "101010001",
		"DescendIconIndex": "5",
		"DescendPhaseIndex1": "-1",
		"DescendPhaseIndex2": "-1",
		"DescendPhaseIndex3": "-1",
		"DescendPhaseIndex4": "-1",
		"DescendPhaseIndex5": "-1"
	},
{
		"Index": "110010005",
		"Grade": "15",
		"DescendType": "11",
		"DescendParam1": "101010002",
		"DescendIconIndex": "4",
		"DescendPhaseIndex1": "-1",
		"DescendPhaseIndex2": "-1",
		"DescendPhaseIndex3": "-1",
		"DescendPhaseIndex4": "-1",
		"DescendPhaseIndex5": "-1"
	},
{
		"Index": "110010006",
		"Grade": "14",
		"DescendType": "11",
		"DescendParam1": "101010003",
		"DescendIconIndex": "6",
		"DescendPhaseIndex1": "101010007",
		"DescendPhaseIndex2": "-1",
		"DescendPhaseIndex3": "-1",
		"DescendPhaseIndex4": "-1",
		"DescendPhaseIndex5": "-1"
	},
{
		"Index": "110010007",
		"Grade": "15",
		"DescendType": "11",
		"DescendParam1": "101010004",
		"DescendIconIndex": "7",
		"DescendPhaseIndex1": "-1",
		"DescendPhaseIndex2": "-1",
		"DescendPhaseIndex3": "-1",
		"DescendPhaseIndex4": "-1",
		"DescendPhaseIndex5": "-1"
	}
]
